automl/__init__.py
automl/__main__.py
automl/balancer.py
automl/business_context.py
automl/business_report.py
automl/calibration.py
automl/cli.py
automl/drift_detection.py
automl/ensemble.py
automl/evaluator.py
automl/exporter.py
automl/gates.py
automl/leakage_detector.py
automl/models.py
automl/pipeline.py
automl/preprocessing.py
automl/profiler.py
automl/progress.py
automl/readiness_scorer.py
automl/statistical_inference.py
automl/task_inference.py
automl/trainer.py
automl/uncertainty.py
tabulaml-0.1.2.dist-info/licenses/LICENSE
tabulaml-0.1.2.dist-info/METADATA
tabulaml-0.1.2.dist-info/WHEEL
tabulaml-0.1.2.dist-info/entry_points.txt
tabulaml-0.1.2.dist-info/top_level.txt
tabulaml-0.1.2.dist-info/RECORD
