Metadata-Version: 2.4
Name: tabulaml
Version: 0.1.2
Summary: TabuLaML - Fast, explainable, no-code AutoML for tabular data
Author-email: Sekpey Herbert <sekpeyherbert@gmail.com>
License: MIT
Project-URL: Homepage, https://github.com/sekpeyherbert/tabulaml
Project-URL: Documentation, https://github.com/sekpeyherbert/tabulaml#readme
Project-URL: Repository, https://github.com/sekpeyherbert/tabulaml
Project-URL: Issues, https://github.com/sekpeyherbert/tabulaml/issues
Keywords: machine-learning,automl,tabular,scikit-learn,xgboost,lightgbm,cli,no-code
Classifier: Development Status :: 4 - Beta
Classifier: Intended Audience :: Developers
Classifier: Intended Audience :: Science/Research
Classifier: Intended Audience :: End Users/Desktop
Classifier: License :: OSI Approved :: MIT License
Classifier: Operating System :: OS Independent
Classifier: Programming Language :: Python :: 3
Classifier: Programming Language :: Python :: 3.9
Classifier: Programming Language :: Python :: 3.10
Classifier: Programming Language :: Python :: 3.11
Classifier: Programming Language :: Python :: 3.12
Classifier: Topic :: Scientific/Engineering :: Artificial Intelligence
Classifier: Topic :: Scientific/Engineering :: Information Analysis
Requires-Python: >=3.9
License-File: LICENSE
Requires-Dist: pandas>=2.0.0
Requires-Dist: numpy>=1.24.0
Requires-Dist: scikit-learn>=1.3.0
Requires-Dist: joblib>=1.3.0
Requires-Dist: matplotlib>=3.7.0
Requires-Dist: seaborn>=0.12.0
Requires-Dist: click>=8.1.0
Requires-Dist: jinja2>=3.1.0
Requires-Dist: imbalanced-learn>=0.11.0
Provides-Extra: boosting
Requires-Dist: xgboost>=2.0.0; extra == "boosting"
Requires-Dist: lightgbm>=4.0.0; extra == "boosting"
Provides-Extra: all
Requires-Dist: xgboost>=2.0.0; extra == "all"
Requires-Dist: lightgbm>=4.0.0; extra == "all"
Provides-Extra: dev
Requires-Dist: pytest>=7.0.0; extra == "dev"
Requires-Dist: pytest-cov>=4.0.0; extra == "dev"
Requires-Dist: black>=23.0.0; extra == "dev"
Requires-Dist: flake8>=6.0.0; extra == "dev"
Dynamic: license-file
